LICENSE
MANIFEST.in
README.md
requirements.txt
setup.py
megspikes/__init__.py
megspikes/conftest.py
megspikes/pipeline.py
megspikes/utils.py
megspikes.egg-info/PKG-INFO
megspikes.egg-info/SOURCES.txt
megspikes.egg-info/dependency_links.txt
megspikes.egg-info/requires.txt
megspikes.egg-info/top_level.txt
megspikes/casemanager/__init__.py
megspikes/casemanager/casemanager.py
megspikes/casemanager/tests/__init__.py
megspikes/casemanager/tests/test_casemanager.py
megspikes/database/__init__.py
megspikes/database/database.py
megspikes/database/tests/__init__.py
megspikes/database/tests/test_database.py
megspikes/detection/__init__.py
megspikes/detection/detection.py
megspikes/detection/tests/__init__.py
megspikes/detection/tests/test_detection.py
megspikes/examples/0_simulation.ipynb
megspikes/examples/1_manual_pipeline.ipynb
megspikes/examples/2_aspire_alphacsc_pipepline.ipynb
megspikes/localization/__init__.py
megspikes/localization/localization.py
megspikes/localization/tests/__init__.py
megspikes/localization/tests/test_localization.py
megspikes/scoring/__init__.py
megspikes/scoring/scoring.py
megspikes/scoring/tests/__init__.py
megspikes/scoring/tests/test_scoring.py
megspikes/simulation/__init__.py
megspikes/simulation/simulation.py
megspikes/simulation/tests/__init__.py
megspikes/simulation/tests/test_simulation.py
megspikes/tests/__init__.py
megspikes/tests/test_full_case.py
megspikes/tests/test_pipeline.py
megspikes/tests/test_utils.py
megspikes/visualization/__init__.py
megspikes/visualization/report.py
megspikes/visualization/visualization.py
megspikes/visualization/tests/__init__.py
megspikes/visualization/tests/test_report.py
megspikes/visualization/tests/test_visualization.py