Metadata-Version: 2.1
Name: megspikes
Version: 0.1.5
Summary: Pipelines for detection epileptic spikes in MEG recording.
Home-page: https://github.com/MEG-SPIKES/megspikes
Author: Valerii Chirkov
Author-email: valerii.chirkov@hu-berlin.de
Maintainer: Valerii Chirkov
Maintainer-email: valerii.chirkov@hu-berlin.de
License: MIT
Download-URL: https://github.com/MEG-SPIKES/megspikes
Platform: any
Classifier: Programming Language :: Python :: 3
Classifier: Intended Audience :: Science/Research
Classifier: Intended Audience :: Developers
Classifier: License :: OSI Approved :: MIT License
Classifier: Topic :: Software Development
Classifier: Topic :: Scientific/Engineering
Classifier: Operating System :: OS Independent
Requires-Python: >=3.7
License-File: LICENSE
